Img2STL/__init__.py
Img2STL/__main__.py
Img2STL/static/__init__.py
Img2STL/static/app_icon.ico
Img2STL/stl/__init__.py
Img2STL/stl/geometry.py
Img2STL/stl/stl_file.py
Img2STL/ui/__init__.py
Img2STL/ui/about_dialog.py
Img2STL/ui/main_frame.py
Img2STL/ui/ui.py
Img2STL/utils/__init__.py
Img2STL/utils/cmd.py
Img2STL/utils/executor.py
Img2STL/utils/logging.py
Img2STL/utils/utils.py
Img2STL/utils/worker.py
Img2STL-1.3.1.dist-info/LICENSE
Img2STL-1.3.1.dist-info/METADATA
Img2STL-1.3.1.dist-info/WHEEL
Img2STL-1.3.1.dist-info/top_level.txt
Img2STL-1.3.1.dist-info/RECORD
