Metadata-Version: 2.1
Name: Img2STL
Version: 1.3.1
Summary: Application for converting images to STL (3D model for printing)
Home-page: https://github.com/baskiton/Img2STL
Author: Alexander Baskikh
Author-email: baskiton@gmail.com
License: MIT
Project-URL: Bug Tracker, https://github.com/baskiton/Img2STL/issues
Platform: UNKNOWN
Classifier: License :: OSI Approved :: MIT License
Classifier: Development Status :: 5 - Production/Stable
Classifier: Environment :: Console
Classifier: Programming Language :: Python :: 3.7
Classifier: Programming Language :: Python :: 3.8
Classifier: Programming Language :: Python :: 3.9
Classifier: Topic :: Multimedia :: Graphics :: 3D Modeling
Requires-Python: >=3.7
License-File: LICENSE
Requires-Dist: numpy (==1.20.3)
Requires-Dist: Pillow (==8.2.0)
Requires-Dist: six (==1.16.0)
Requires-Dist: wxPython (==4.1.1) ; platform_system != "Linux"
